{"id":574,"name":"唐珙","dynasty":"元代","simpleIntro":"唐珙，字温如，元末明初詩人，會稽山陰（今浙江紹興）人。其父南宋義士、詞人唐珏在至元中與林景熙收拾宋陵遺骨，重新安葬，並植冬青為識。在鄉里以詩知名，但所作傳世不多。生平僅略見於《御選元詩》卷首《姓名爵裏》 、《元詩選補遺》小傳。","detailIntro":"{\"著述\":\"　　元代詩人唐珙生平無記載，僅知“珙豪於詩”。他父親唐珏是南宋義士，曾於元僧盜掘南宋皇陵之時，偷拾諸帝遺骨並重新安葬，使得免受元僧褻瀆，直至朱元璋方重修宋陵安葬。雖是元代人，唐珙也應受其父教，知俠義，亦可謂南宋遺民。\\n\\n　　唐珙僅有八首詩記載下來。\\n\\n　　《墨蘭》，“瑤階夢結翠宜男，誤墮仙人紫玉簪”，可見喜歡蘭草。\\n\\n　　《貓》，“牡丹架暖眠春晝，薄荷香濃醉曉晴”，可見喜歡貓。\\n\\n　　《澄碧堂》 ，“玲瓏鑿開雲霧窗，悟作虛空大圓鏡”，可見沉迷於禪宗。\\n\\n　　《題海嶽後人煙巒曉景圖》，“須臾筆硯間，淋漓走元氣”，懂得畫畫。\\n\\n　　《趙文敏書洛神賦》，“宓妃夜走天吳奔，驪龍騰驤老蛟舞”，痴迷書法。\\n\\n　　《題龍陽縣青草湖》，“醉後不知天在水，滿船清夢壓星河”，因何醉呢？\\n\\n　　《韓左軍馬圖卷》，“太平此馬惜遺棄，往往駑駘歸天閒”，復國夢嗎？\\n\\n　　《題王逸老書飲中八仙歌》，“摩娑故紙嘆凋落，老眼昏花猶可認”，一生竟短。\\n\\n　　唐珙是沒有傳記的，於《全唐詩》誤收後更流傳為“沒有片言隻語的記載”。而八首詩後，已然栩栩如生。\\n\\n　　又“澄碧堂” ，南宋皇宮有此堂；“海嶽”，北宋米芾號“海嶽外史”；“文敏”系南宋趙孟頫諡號；“王逸老”是南宋書法家；而青草湖中“湘君白髮”，應是學自其父詞“‘斑竹’臨江首重回”中之典故，追思故國也。蓋追思之人也。\\n\\n　　南宋遺民，無謂志遠，無緣仕途愁憂，蘭、貓、禪、畫、書，一醉，一夢，一生，然卻正因如此，他不沾半點功名，竟成一境界之詩——不曾“人生”過，惟曾“人格”過。\\n\\n　　關羽，是“千里行”後的英雄；唐僧，是“取真經”後的聖僧。而他，是“不入世”的詩人，是“一直”着的詩人，是永恆。 ▲\\n\\n\"}","headImageUrl":"","poemIds":[794]}