{"id":778,"name":"宋琬","dynasty":"清代","simpleIntro":"宋琬（1614～1674）清初著名詩人，清八大詩家之一。字玉叔，號荔裳，漢族，萊陽（今屬山東）人。順治四年進士，授户部主事，累遷永平兵僕道、寧紹台道。族子因宿憾，誣其與聞逆謀，下獄三年。久之得白，流寓吳、越間，尋起四川按察使。琬詩入杜、韓之室，與施閏章齊名，有南施北宋之目，又與嚴沆、施閏章、丁澎等合稱為燕台七子，著有《安雅堂集》及《二鄉亭詞》。","detailIntro":"{\"成就\":\"詩作特色\\n　　宋琬詩在清初頗有名，早年在京師吏部任職時，就與給事中嚴沆、部郎施閏章、丁澎等人經常唱和，名滿京師，時有“燕台七子”之稱。王士禎《池北偶談》説：“康熙以來詩人，無出南施北宋之右，宣城施閏章愚山，萊陽宋琬荔裳是也。”又説他後期詩歌，頗得力於杜甫、韓愈、陸游。沈德潛《清詩別裁》説：“宋以雄健磊落勝”。楊際昌在《國朝詩話》卷一中説：“施（施閏章）如良玉之温潤而慄，宋如豐城寶劍，時露光氣。”宋琬詩很少反映現實之作，內容當然不能和杜甫、陸游相比擬，只是在語言風格上有所仿效而已。他的詩作內容大多抒寫個人的窮愁、哀傷，也有一些暗寓故國之思的作品。《聽鐘鳴》一詩中寫道：“聽鐘鳴，所聽非一聲；一聲才到枕，雙淚無縱橫。白頭老鳥作鬼語，羣飛啞啞還相驚。”寫的悽惋動人，有較強的藝術感染力。他的詩中也有不少揭露封建王朝的黑暗，反映民眾的苦難及美好願望的作品，具有一定的人民性。在《漁家詞》一詩中，詩人憤怒地揭露了租吏的兇相與貪婪，反映漁民生活的艱難，讀之催人淚下。在《同歐陽令同飲鳳凰山下》一詩中寫道：“茅茨深處隔煙霞，雞犬寥寥有數家。寄語武陵仙吏到，莫將徵税得桃花。”表達了詩人的美好願望。\\n　　宋琬的詩在藝術上是有較高造詣的，古體詩和律詩寫得尤好。用語奇麗，比喻清新，委婉含蓄，屬對工巧，極為時人所推崇。稱之為“詩人之雄”，有人贊為“東海之偉人”。與他同時代的金之俊，在為《安雅堂集》所做的序中説：他的詩“其識宏，其慮遠，其情長，其氣清以厚，其調雋以永，其格嚴以老，其言確以質，殆有如懷沙遠遊，屈子悲憤之所感乎。”《庚寅臘月讀子美同谷七歌效其體以詠哀》、《寫哀》、《獄中對月》、《晨星嘆》、《埋憂》、《聽鐘鳴》、《悲落葉》等為其代表作品。他的詩作以雄渾見長。《安雅堂全集》20卷，其中包括《安雅堂未刻稿》、《入蜀集》、《二鄉亭詞》以及雜劇《祭皋陶》等。\\n\\n著述名錄\\n　　宋琬一生著述很多，現在能見到的詩有1333首，詞165首，文223篇，此外還有賦2篇、劇本一個，均收在《安雅堂集》裏。《安雅堂全集》包括《安雅堂未刻稿》《入蜀集》《二鄉亭詞》以及雜劇《祭皋陶》等。萊陽市圖書館現存《安雅堂集》16卷，其木刻版尚保藏數百片之多。 ▲\\n\\n\"}","headImageUrl":"https://guwen-1252396323.cos.ap-chengdu.myqcloud.com/headImage/20180914152647484.jpg","poemIds":[6005]}