{"id":1705,"title":"雜詩","writer":"佚名","writerId":0,"dynasty":"唐代","content":"勸君莫惜金縷衣，勸君須惜少年時。\n有花堪折直須折，莫待無花空折枝。\n\n青天無雲月如燭，露泣梨花白如玉。\n子規一夜啼到明，美人獨在空房宿。\n\n空賜羅衣不賜恩，一薰香後一銷魂。\n雖然舞袖何曾舞，常對春風裛淚痕。\n\n不洗殘妝憑繡牀，也同女伴繡鴛鴦。\n回針刺到雙飛處，憶著征夫淚數行。\n\n眼想心思夢裏驚，無人知我此時情。\n不如池上鴛鴦鳥，雙宿雙飛過一生。\n\n一去遼陽系夢魂，忽傳徵騎到中門。\n紗窗不肯施紅粉，徒遣蕭郎問淚痕。\n\n鶯啼露冷酒初醒，罨畫樓西曉角鳴。\n翠羽帳中人夢覺，寶釵斜墜枕函聲。\n\n行人南北分徵路，流水東西接御溝。\n終日坡前怨離別，謾名長樂是長愁。\n\n偏倚繡牀愁不起，雙垂玉箸翠鬟低。\n捲簾相待無消息，夜合花前日又西。\n\n悔將淚眼向東開，特地愁從望裏來。\n三十六峯猶不見，況伊如燕這身材。\n\n滿目笙歌一段空，萬般離恨總隨風。\n多情為謝殘陽意，與展晴霞片片紅。\n\n兩心不語暗知情，燈下裁縫月下行。\n行到階前知未睡，夜深聞放剪刀聲。\n\n近寒食雨草萋萋，著麥苗風柳映堤。\n早是有家歸未得，杜鵑休向耳邊啼。\n\n水紋珍簟思悠悠，千里佳期一夕休。\n從此無心愛良夜，任他明月下西樓。\n\n數日相隨兩不忘，郎心如妾妾如郎。\n出門便是東西路，把取紅箋各斷腸。\n\n無定河邊暮角聲，赫連台畔旅人情。\n函關歸路千餘裏，一夕秋風白髮生。\n\n花落長川草色青，暮山重疊兩冥冥。\n逢春便覺飄蓬苦，今日分飛一涕零。\n\n洛陽才子鄰簫恨，湘水佳人錦瑟愁。\n今昔兩成惆悵事，臨邛春盡暮江流。\n\n浙江輕浪去悠悠，望海樓吹望海愁。\n莫怪鄉心隨魄斷，十年為客在他州。\n\n","translation":"其一\n我勸你不要顧惜華貴的金縷衣，我勸你一定要珍惜青春少年時。\n花開宜折的時候就要抓緊去折，不要等到花謝時只折了個空枝。\n\n其十三\n時令將近寒食，春雨綿綿春草萋萋；春風過處苗麥搖擺，堤上楊柳依依。\n這是為什麼啊，此前我有家卻歸去不得。杜鵑啊，不要在我耳邊不停地悲啼。\n\n","remark":"其一\n金縷衣：綴有金線的衣服，比喻榮華富貴。\n堪：可以，能夠。\n直須：不必猶豫。直：直接，爽快。\n莫待：不要等到。\n\n其十三\n著：吹入。\n早是：此前。\n杜鵑：鳥名，即子規。\n休：不要。\n\n","shangxi":"","typeIds":[4]}