{"id":4809,"title":"吾琴所為曹令所壞寓居賦秋風破屋歌","writer":"佚名","writerId":0,"dynasty":"元代","content":"君不見南山叟，一室容身小如鬥。閉門僵卧學袁安，雪打風吹懶開口。\n\n又不見牛馬走，短布單衣寒露肘。長途汨沒笑李斯，咸陽市上牽黃狗。\n\n男兒壯志要似渭川雲夢竹，不染塵埃出林麓。又似蒼顏勁節松，偃蹇孤高立巖谷。\n\n雪中矯矯舞游龍，霜裏涓涓濯寒玉。春和長有拂雲青，歲寒豈減昂霄綠。\n\n野人曠蕩無所歸，居無華屋膳無肉。胸涵膽氣欲食牛，世乏才能恥幹祿。\n\n高眼不復夢功名，信步何曾限南北。行藏無礙獨縱橫，動靜隨緣少拘束。\n\n從來任運合天真，坦率人皆笑粗俗。儒生性僻不入時，身老乾坤忘寵辱。\n\n囊虛買譽百兩金，日糴充飢五升粟。頑然空洞腰十圍，唯貯文章滿斯腹。\n\n謾開電目燭五行，徒援霜毫寫千幅。祗聞張奉賤毛生，未見夷吾憐鮑叔。\n\n短琴一弄固有餘，長鋏三彈常不足。噫戲安得樂天都蓋洛陽城裏萬丈之白裘，杜陵大庇天下寒士萬間之廣屋。\n\n尊賢重道貽今羞，大廈寬袍遂吾欲。牀頭更有酒新熟，綠蟻濡唇斟百斛。\n\n此時不願萬户侯，何心更作九州牧。山中宰相樂餘年，管領丘園慰幽獨。\n\n雲邊吟詠足逍遙，月下壺觴倍清淑。閒鋪棋局伴爐薰，滿吸湖光飲山淥。\n\n含煙細草疊芳茵，過雨餘花呈繡褥。王侯卿相非我儔，牧圉樵漁是予屬。\n\n四時佳景盡來歸，泉石煙霞皆素蓄。笑拖長袖醉春風，寄傲軒窗百斯福。\n\n","translation":"","remark":"","shangxi":"","typeIds":[]}